{
  "version": "0.3.14-fixed",
  "steps": [
    {
      "tag": "CreateDirective",
      "location": {
        "path": {
          "tag": "Field",
          "model": "Post",
          "field": "updatedAt"
        },
        "directive": "updatedAt"
      }
    },
    {
      "tag": "DeleteDirective",
      "location": {
        "path": {
          "tag": "Field",
          "model": "Post",
          "field": "updatedAt"
        },
        "directive": "default"
      }
    },
    {
      "tag": "CreateDirective",
      "location": {
        "path": {
          "tag": "Field",
          "model": "Tag",
          "field": "updatedAt"
        },
        "directive": "updatedAt"
      }
    },
    {
      "tag": "DeleteDirective",
      "location": {
        "path": {
          "tag": "Field",
          "model": "Tag",
          "field": "updatedAt"
        },
        "directive": "default"
      }
    }
  ]
}